flexypy/__init__.py
flexypy/cli.py
flexypy/exceptions/__init__.py
flexypy/exceptions/baseexceptions.py
flexypy/exceptions/extension.py
flexypy/exceptions/render.py
flexypy/exceptions/routing.py
flexypy/exceptions/server.py
flexypy/exceptions/web/__init__.py
flexypy/exceptions/web/baseexseptions.py
flexypy/exceptions/web/server.py
flexypy/generate_templates/__init__.py
flexypy/generate_templates/generator.py
flexypy/generate_templates/templates/__init__.py
flexypy/generate_templates/templates/main.py
flexypy/generate_templates/templates/config/__init__.py
flexypy/generate_templates/templates/config/apps.py
flexypy/generate_templates/templates/config/dirs.py
flexypy/http/__init__.py
flexypy/http/cookie.py
flexypy/http/request.py
flexypy/http/routing.py
flexypy/http/server.py
flexypy/http/template/__init__.py
flexypy/http/template/render.py
flexypy/http/template/extensions/__init__.py
flexypy/http/template/extensions/base_extension.py
flexypy/http/template/extensions/template_ext.py
flexypy/middlewares/__init__.py
flexypy/middlewares/mddl.py
flexypy-0.1.1.dist-info/METADATA
flexypy-0.1.1.dist-info/WHEEL
flexypy-0.1.1.dist-info/top_level.txt
flexypy-0.1.1.dist-info/RECORD
