Metadata-Version: 2.1
Name: flexypy
Version: 0.1.1
Summary: Web framework.
Classifier: Programming Language :: Python :: 3
Requires-Python: >=3.7
Requires-Dist: gunicorn
Requires-Dist: Jinja2
Requires-Dist: fire
Requires-Dist: cryptography
